windowpackage/__init__.py
windowpackage/windows_canny.py
windowpackage/windows_rename.py
windowpackage-0.2.0.dist-info/METADATA
windowpackage-0.2.0.dist-info/WHEEL
windowpackage-0.2.0.dist-info/top_level.txt
windowpackage-0.2.0.dist-info/RECORD
