Metadata-Version: 2.1
Name: windowpackage
Version: 0.2.0
Summary: A package for image processing and file renaming
Home-page: https://github.com/peggy2125/windows_rdrcpackage.git
Classifier: Programming Language :: Python :: 3
Classifier: License :: OSI Approved :: MIT License
Classifier: Operating System :: OS Independent
Requires-Python: >=3.6
Requires-Dist: opencv-python
Requires-Dist: numpy
